single_ins/__init__.py
single_ins/equalable_si.py
single_ins/hashable_si.py
single_ins/si.py
single_ins-0.0.1.dist-info/METADATA
single_ins-0.0.1.dist-info/WHEEL
single_ins-0.0.1.dist-info/top_level.txt
single_ins-0.0.1.dist-info/RECORD
