Metadata-Version: 2.1
Name: single-ins
Version: 0.0.1
Summary: Single Instance
Home-page: https://github.com/lichunown/single-ins
Author: lcy
Author-email: lichunyang_1@outlook.com
Classifier: Programming Language :: Python :: 3
Classifier: License :: OSI Approved :: MIT License
Classifier: Operating System :: OS Independent
